[
{"拍卖时间":"2002年1月","投放数量":1400,"最低成交价":13600,"平均成交价":14735,"投标人数":3718},
{"拍卖时间":"2002年2月","投放数量":1800,"最低成交价":13100,"平均成交价":14057,"投标人数":4590},
{"拍卖时间":"2002年3月","投放数量":2000,"最低成交价":14300,"平均成交价":14662,"投标人数":5190},
{"拍卖时间":"2002年4月","投放数量":2300,"最低成交价":16000,"平均成交价":16334,"投标人数":4806},
{"拍卖时间":"2002年5月","投放数量":2350,"最低成交价":17800,"平均成交价":18357,"投标人数":4665},
{"拍卖时间":"2002年6月","投放数量":2800,"最低成交价":19600,"平均成交价":20178,"投标人数":4502},
{"拍卖时间":"2002年7月","投放数量":3000,"最低成交价":19800,"平均成交价":20904,"投标人数":3774},
{"拍卖时间":"2002年8月","投放数量":3000,"最低成交价":21000,"平均成交价":21601,"投标人数":4640},
{"拍卖时间":"2002年9月","投放数量":3200,"最低成交价":23600,"平均成交价":24040,"投标人数":4393},
{"拍卖时间":"2002年10月","投放数量":3200,"最低成交价":26400,"平均成交价":27040,"投标人数":4661},
{"拍卖时间":"2002年11月","投放数量":3200,"最低成交价":30800,"平均成交价":31721,"投标人数":4021},
{"拍卖时间":"2002年12月","投放数量":3600,"最低成交价":100,"平均成交价":27848,"投标人数":3525}
]
